cligen/__init__.py
cligen/__main__.py
cligen/cligen.py
cligen/cligen0argparse.py
cligen/cligen0python.py
cligen/scanner.py
cligen-0.5.4.dist-info/LICENSE
cligen-0.5.4.dist-info/METADATA
cligen-0.5.4.dist-info/WHEEL
cligen-0.5.4.dist-info/entry_points.txt
cligen-0.5.4.dist-info/top_level.txt
cligen-0.5.4.dist-info/RECORD
